pyconarr/__init__.py
pyconarr/libs/__init__.py
pyconarr/libs/config.py
pyconarr/libs/docs.py
pyconarr/libs/jellyfin.py
pyconarr/libs/route.py
pyconarr/main.py
pyconarr-0.4.56.dist-info/LICENSE
pyconarr-0.4.56.dist-info/METADATA
pyconarr-0.4.56.dist-info/WHEEL
pyconarr-0.4.56.dist-info/RECORD
