Metadata-Version: 2.1
Name: pyconarr
Version: 0.4.56
Summary: 
License: GPLv3
Author: Clem
Author-email: author@clem.fr
Requires-Python: >=3.10,<4.0
Classifier: License :: Other/Proprietary License
Classifier: Programming Language :: Python :: 3
Classifier: Programming Language :: Python :: 3.10
Classifier: Programming Language :: Python :: 3.11
Classifier: Programming Language :: Python :: 3.12
Classifier: Programming Language :: Python :: 3.13
Requires-Dist: fastapi (==0.120.0)
Requires-Dist: pyyaml (>=6.0.1,<7.0.0)
Requires-Dist: requests (>=2.31.0,<3.0.0)
Requires-Dist: setuptools (>=80.0.0,<81.0.0)
Requires-Dist: toml (>=0.10.2,<0.11.0)
Requires-Dist: uvicorn (>=0.38.0,<0.39.0)
